doot/__init__.py
doot/__main__.py
doot/_interface.py
doot/enums.py
doot/errors.py
doot/index.rst
doot/structs.py
doot/__data/aliases.toml
doot/__data/constants.toml
doot/__docs/architecture.rst
doot/__docs/cli.rst
doot/__docs/conf.py
doot/__docs/faq.rst
doot/__docs/getting_started.rst
doot/__docs/glossary.rst
doot/__docs/license.rst
doot/__docs/rst_tests.rst
doot/__docs/_static/custom.css
doot/__docs/_static/test.csv
doot/__docs/_templates/autoapi/python/attribute.rst
doot/__docs/_templates/autoapi/python/class.rst
doot/__docs/_templates/autoapi/python/data.rst
doot/__docs/_templates/autoapi/python/debug_obj.rst.jinja
doot/__docs/_templates/autoapi/python/exception.rst
doot/__docs/_templates/autoapi/python/function.rst
doot/__docs/_templates/autoapi/python/method.rst
doot/__docs/_templates/autoapi/python/module.rst
doot/__docs/_templates/autoapi/python/package.rst
doot/__docs/_templates/autoapi/python/property.rst
doot/__docs/_templates/autoapi/python/vis_attrs.rst.jinja
doot/__docs/_templates/autoapi/python/vis_classes.rst.jinja
doot/__docs/_templates/autoapi/python/vis_enums.rst.jinja
doot/__docs/_templates/autoapi/python/vis_excs.rst.jinja
doot/__docs/_templates/autoapi/python/vis_funcs.rst.jinja
doot/__docs/_templates/autoapi/python/vis_protos.rst.jinja
doot/__docs/_templates/autoapi/python/vis_types.rst.jinja
doot/__docs/_templates/autosummary/base.rst
doot/__docs/_templates/autosummary/class.rst
doot/__docs/_templates/autosummary/module.rst
doot/__docs/examples/actions.rst
doot/__docs/examples/commands.rst
doot/__docs/examples/dootfile.rst
doot/__docs/examples/jobs.rst
doot/__docs/examples/keys.rst
doot/__docs/examples/overview.rst
doot/__docs/examples/plugins.rst
doot/__docs/examples/precommit.rst
doot/__docs/examples/tasks.rst
doot/__docs/misc/comparison.rst
doot/__docs/misc/names.rst
doot/__docs/misc/overview.rst
doot/__docs/misc/state.rst
doot/__docs/reference/actions.rst
doot/__docs/reference/commands.rst
doot/__docs/reference/enums.rst
doot-1.1.1.dist-info/licenses/LICENSE
doot-1.1.1.dist-info/METADATA
doot-1.1.1.dist-info/WHEEL
doot-1.1.1.dist-info/entry_points.txt
doot-1.1.1.dist-info/top_level.txt
doot-1.1.1.dist-info/RECORD
