Metadata-Version: 2.4
Name: doot
Version: 1.1.1
Summary: An opinionated, TOML based task runner
Author-email: jgrey <jgrey.n.plus.one@gmail.com>
Project-URL: homepage, https://github.com/jgrey4296/doot
Project-URL: documentation, https://doot.readthedocs.io/en/latest/
Project-URL: repository, https://github.com/jgrey4296/doot
Project-URL: changelog, https://github.com//doot/blob/master/CHANGELOG.md
Keywords: toml,taskrunner
Classifier: Programming Language :: Python
Classifier: Programming Language :: Python :: 3.11
Classifier: Development Status :: 3 - Alpha
Classifier: Topic :: Utilities
Requires-Python: >=3.12
License-File: LICENSE
Requires-Dist: networkx>3.0
Requires-Dist: sh>=2.0.6
Requires-Dist: stackprinter>=0.2.10
Requires-Dist: sty>=1.0.0
Requires-Dist: boltons>=23.0.0
Requires-Dist: pydantic>=2.7.0
Requires-Dist: jgdv>=1.0.0
Requires-Dist: matplotlib>=3.10.1
Requires-Dist: packaging>=24.2
Provides-Extra: dev
Requires-Dist: myst-parser>=4.0.1; extra == "dev"
Requires-Dist: pytest>=8.3.5; extra == "dev"
Requires-Dist: pytest-mock>=3.14.0; extra == "dev"
Requires-Dist: sphinx>=8.2.3; extra == "dev"
Requires-Dist: sphinx-rtd-theme>=3.0.2; extra == "dev"
Dynamic: license-file
